{
  "type": "minecraft:crafting_shapeless",
  "category": "misc",
  "ingredients": [
    {
      "item": "ewmedieval:burzum_steel_nugget"
    },
    {
      "item": "ewmedieval:burzum_steel_nugget"
    },
    {
      "item": "ewmedieval:burzum_steel_nugget"
    },
    {
      "item": "ewmedieval:burzum_steel_nugget"
    },
    {
      "item": "ewmedieval:burzum_steel_nugget"
    },
    {
      "item": "ewmedieval:burzum_steel_nugget"
    },
    {
      "item": "ewmedieval:burzum_steel_nugget"
    },
    {
      "item": "ewmedieval:burzum_steel_nugget"
    },
    {
      "item": "ewmedieval:burzum_steel_nugget"
    }
  ],
  "result": {
    "item": "ewmedieval:burzum_steel_ingot"
  }
}